healthupdates/__init__.py
healthupdates/updates.py
healthupdates/test/__init__.py
healthupdates/test/test_updater.py
HealthUpdates-0.1.2.dist-info/LICENSE.txt
HealthUpdates-0.1.2.dist-info/METADATA
HealthUpdates-0.1.2.dist-info/WHEEL
HealthUpdates-0.1.2.dist-info/entry_points.txt
HealthUpdates-0.1.2.dist-info/top_level.txt
HealthUpdates-0.1.2.dist-info/RECORD
