Metadata-Version: 2.1
Name: HealthUpdates
Version: 0.1.2
Summary: Python script that retrieves COVID-19 data from an API
Home-page: UNKNOWN
Author: Timothy Clark
Author-email: timothy@rzerotracing.com
License: Creative Commons Attribuion-Noncommercial-Share Alike license
Platform: UNKNOWN
Classifier: Programming Language :: Python :: 3
Classifier: Operating System :: OS Independent
Requires-Dist: requests
